{"name":"Mousefart","tagline":"HAS SCIENCE GONE TOO FAR???","body":"mousefart.js\r\n============\r\n##The flatulent JQuery plugin based on [The Onion's fartscroll.js](http://theonion.github.io/fartscroll.js/)\r\n\r\nDescription\r\n-----------\r\n\r\nThis plugins causes extreme defecation and flatulence of your mouse (or finger for you touchpad users) onto the unfortunate element. \r\n\r\n\r\n\r\n\r\n\r\nUsage\r\n-----\r\n\r\n###Applying farts to a document.\r\n`$(document).mousefart()`\r\n\r\n\r\n###Applying farts to elements.\r\n`$('#someSmellySpan').mousefart()`\r\n\r\n`$('.tacos').mousefart()`\r\n\r\n\r\n","google":"UA-39251932-1","note":"Don't delete this file! It's used internally to help with page regeneration."}